README.md
pyproject.toml
setup.cfg
setup.py
ewoksserver/__init__.py
ewoksserver/static/asset-manifest.json
ewoksserver/static/favicon.ico
ewoksserver/static/index.html
ewoksserver/static/robots.txt
ewoksserver/static/static/css/2.679831fc.chunk.css
ewoksserver/static/static/css/2.679831fc.chunk.css.map
ewoksserver/static/static/css/main.d9c82a2b.chunk.css
ewoksserver/static/static/css/main.d9c82a2b.chunk.css.map
ewoksserver/static/static/js/2.989e4250.chunk.js
ewoksserver/static/static/js/2.989e4250.chunk.js.LICENSE.txt
ewoksserver/static/static/js/2.989e4250.chunk.js.map
ewoksserver/static/static/js/main.5fbc1284.chunk.js
ewoksserver/static/static/js/main.5fbc1284.chunk.js.map
ewoksserver/static/static/js/runtime-main.551be916.js
ewoksserver/static/static/js/runtime-main.551be916.js.map
ewoksserver/static/static/media/AggregateColumns.88d7fa21.svg
ewoksserver/static/static/media/Continuize.355db9c3.svg
ewoksserver/static/static/media/Correlations.944dc633.svg
ewoksserver/static/static/media/CreateClass.9bfeecf8.svg
ewoksserver/static/static/media/down.c4ef096f.svg
ewoksserver/static/static/media/graphInput.8ffbf308.svg
ewoksserver/static/static/media/graphOutput.287d41af.svg
ewoksserver/static/static/media/left.37aaff4e.svg
ewoksserver/static/static/media/right.5d5ae196.svg
ewoksserver/static/static/media/up.a947387a.svg
ewoksweb/__init__.py
ewoksweb.egg-info/PKG-INFO
ewoksweb.egg-info/SOURCES.txt
ewoksweb.egg-info/dependency_links.txt
ewoksweb.egg-info/namespace_packages.txt
ewoksweb.egg-info/requires.txt
ewoksweb.egg-info/top_level.txt