Metadata-Version: 2.1
Name: ewoksweb
Version: 0.0.1a2
Summary: Backend for ewoksweb
Home-page: https://gitlab.esrf.fr/workflow/ewoks/ewoksweb
Author: ESRF
Author-email: giannis.koumoutsos@esrf.fr
License: MIT
Project-URL: Documentation, https://workflow.gitlab-pages.esrf.fr/ewoks/ewoksweb
Project-URL: Tracker, https://gitlab.esrf.fr/workflow/ewoks/ewoksweb/issues
Project-URL: Source, https://gitlab.esrf.fr/workflow/ewoks/ewoksweb
Platform: UNKNOWN
Classifier: Intended Audience :: Science/Research
Classifier: License :: OSI Approved :: MIT License
Classifier: Programming Language :: Python :: 3
Requires-Python: >=3.5
Provides-Extra: dev
Provides-Extra: doc
